PyBazooStore/__init__.py
PyBazooStore/bazoo_store.py
PyBazooStore/searched_by.py
pybazoostore-1.4.0.dist-info/licenses/LICENSE
pybazoostore-1.4.0.dist-info/METADATA
pybazoostore-1.4.0.dist-info/WHEEL
pybazoostore-1.4.0.dist-info/top_level.txt
pybazoostore-1.4.0.dist-info/RECORD
