Metadata-Version: 2.4
Name: PyBazooStore
Version: 1.4.0
Summary: This library is designed to work with the Bazvastr service on the Bale messenger, and you can use it in projects such as bot search and more .
Author: MohammadReza
Author-email: narnama.room@gmail.com
Project-URL: صفحه من ❤️, https://apicode.pythonanywhere.com/
Project-URL: سایت اصلی 🌐, https://webapp.bazoostore.ir/
Classifier: Programming Language :: Python :: 3
Classifier: License :: OSI Approved :: MIT License
Classifier: Operating System :: OS Independent
Requires-Python: >=3.5
License-File: LICENSE
Requires-Dist: requests
Dynamic: author
Dynamic: author-email
Dynamic: classifier
Dynamic: description
Dynamic: description-content-type
Dynamic: license-file
Dynamic: project-url
Dynamic: requires-dist
Dynamic: requires-python
Dynamic: summary
